VHDL/NAND_RS_VHDL/nand_rs.vhdl
--libraries
LIBRARY IEEE;
USE IEEE.std_logic_1164.ALL;

--entity
ENTITY nand_rs IS
    PORT (
        rn, sn : IN STD_LOGIC;
        qn, q : OUT STD_LOGIC
    );
END ENTITY;

--Architecture
ARCHITECTURE v1 OF nand_rs IS
    SIGNAL qn_internal : STD_LOGIC;

BEGIN
    PROCESS (rn, sn)
    BEGIN
        IF (rn = '0') THEN
            qn_internal <= '1';
        ELSIF (sn = '0') THEN
            qn_internal <= '0';
        END IF;
    END PROCESS;

    q <= NOT qn_internal;
    qn <= qn_internal;
END ARCHITECTURE;

VHDL/NAND_RS_VHDL/nand_rs_tb.vhdl
--libraries
LIBRARY IEEE;
USE IEEE.std_logic_1164.ALL;

--entity
ENTITY nand_rs_tb IS
END ENTITY;

--architecture
ARCHITECTURE tb OF nand_rs_tb IS
    COMPONENT nand_rs
        PORT (
            rn, sn : IN STD_LOGIC;
            qn, q : OUT STD_LOGIC
        );
    END COMPONENT;

    SIGNAL rn_tb, sn_tb, qn_tb, q_tb : STD_LOGIC;

BEGIN

    --port mapping
    tb : nand_rs PORT MAP(
        rn => rn_tb,
        sn => sn_tb,
        qn => qn_tb,
        q => q_tb
    );

    --testbench
    PROCESS BEGIN
        rn_tb <= '1';
        sn_tb <= '1';
        WAIT FOR 1 ns;

        rn_tb <= '0';
        sn_tb <= '1';
        WAIT FOR 1 ns;

        rn_tb <= '1';
        sn_tb <= '1';
        WAIT FOR 1 ns;

        rn_tb <= '1';
        sn_tb <= '0';
        WAIT FOR 1 ns;

        rn_tb <= '1';
        sn_tb <= '1';
        WAIT FOR 1 ns;

        rn_tb <= '1';
        sn_tb <= '0';
        WAIT FOR 1 ns;

        rn_tb <= '1';
        sn_tb <= '1';
        WAIT FOR 1 ns;

        rn_tb <= '0';
        sn_tb <= '1';
        WAIT FOR 2 ns;

    END PROCESS;

END tb;

VHDL/NAND_RS_VHDL/sim1.vcd
$date
  Fri Jan 14 17:42:26 2022
$end
$version
  GHDL v0
$end
$timescale
  1 fs
$end
$scope module standard $end
$upscope $end
$scope module std_logic_1164 $end
$upscope $end
$scope module nand_rs_tb $end
$var reg 1 ! rn_tb $end
$var reg 1 " sn_tb $end
$var reg 1 # qn_tb $end
$var reg 1 $ q_tb $end
$scope module tb $end
$var reg 1 % rn $end
$var reg 1 & sn $end
$var reg 1 ' qn $end
$var reg 1 ( q $end
$var reg 1 ) qn_internal $end
$upscope $end
$upscope $end
$enddefinitions $end
#0
1!
1"
U#
U$
1%
1&
U'
U(
U)
#1000000
0!
1#
0$
0%
1'
0(
1)
#2000000
1!
1%
#3000000
0"
0#
1$
0&
0'
1(
0)
#4000000
1"
1&
#5000000
0"
0&
#6000000
1"
1&
#7000000
0!
1#
0$
0%
1'
0(
1)
#9000000
1!
1%
#10000000
0!
0%
#11000000
1!
1%
#12000000
0"
0#
1$
0&
0'
1(
0)
#13000000
1"
1&
#14000000
0"
0&
#15000000
1"
1&
#16000000
0!
1#
0$
0%
1'
0(
1)
#18000000
1!
1%
#19000000
0!
0%
#20000000
1!
1%
