TestFolder/SHIFTREGISTER_VHDL/SHIFTREGISTER.vhdl
LIBRARY ieee;
USE ieee.std_logic_1164.ALL;

ENTITY SHIFTREGISTER IS
    PORT (
        clk, S : IN STD_LOGIC;
        P : OUT STD_LOGIC_VECTOR(7 DOWNTO 0)
    );
END ENTITY;

ARCHITECTURE arch OF SHIFTREGISTER IS
    SIGNAL P_in : STD_LOGIC_VECTOR(7 DOWNTO 0);

BEGIN

    PROCESS (clk)
    BEGIN

        P_in(0) <= S;
        P_in(1) <= P_in(0);
        P_in(2) <= P_in(1);
        P_in(3) <= P_in(2);
        P_in(4) <= P_in(3);
        P_in(5) <= P_in(4);
        P_in(6) <= P_in(5);
        P_in(7) <= P_in(6);

    END PROCESS;

    P <= P_in;

END arch;

TestFolder/SHIFTREGISTER_VHDL/SHIFTREGISTER_tb.vhdl
LIBRARY ieee;
USE ieee.std_logic_1164.ALL;

ENTITY SHIFTREGISTER_TB IS
END SHIFTREGISTER_TB;

ARCHITECTURE arch OF SHIFTREGISTER_TB IS

    COMPONENT SHIFTREGISTER IS
        PORT (
            clk, S : IN STD_LOGIC;
            P : OUT STD_LOGIC_VECTOR(7 DOWNTO 0)
        );
    END COMPONENT;

    SIGNAL clk : STD_LOGIC := '0';
    SIGNAL S : STD_LOGIC := '0';
    SIGNAL P : STD_LOGIC_VECTOR(7 DOWNTO 0);

    CONSTANT clk_period : TIME := 10 fs;

BEGIN

    sr : SHIFTREGISTER PORT MAP(clk => clk, S => S, P => P);

    PROCESS
    BEGIN

        clk <= '0';
        WAIT FOR clk_period/2;

        S <= '1';
        WAIT FOR clk_period/2;

        clk <= '1';

        WAIT FOR clk_period/2;

        S <= '0';

        WAIT FOR clk_period/2;

        clk <= '0';

        WAIT FOR clk_period;

        clk <= '1';

        WAIT FOR clk_period;

        clk <= '0';

        WAIT FOR clk_period/2;

        S <= '1';

        WAIT FOR clk_period/2;

        clk <= '1';

        WAIT FOR clk_period;

        clk <= '0';

        WAIT FOR clk_period;

        clk <= '1';

        WAIT FOR clk_period;

        clk <= '0';

        WAIT FOR clk_period;

        clk <= '1';

        WAIT FOR clk_period/2;

        S <= '0';

        WAIT FOR clk_period/2;

        S <= '1';
        clk <= '0';

        WAIT FOR clk_period/2;

        S <= '0';

        WAIT FOR clk_period/2;

        clk <= '1';

        WAIT FOR clk_period/2;

        S <= '1';

        WAIT FOR clk_period/2;

        clk <= '0';

        WAIT FOR clk_period/2;

        S <= '0';

        WAIT FOR clk_period/2;

        clk <= '1';

        WAIT FOR clk_period/2;

        S <= '1';

        WAIT FOR clk_period/2;

        clk <= '0';

        WAIT FOR clk_period;

        clk <= '1';

        WAIT FOR clk_period;

        clk <= '0';

        WAIT FOR clk_period;

        clk <= '1';

        WAIT FOR clk_period/2;

        S <= '0';

        WAIT FOR clk_period/2;

        clk <= '0';

        WAIT FOR clk_period;

    END PROCESS;


END arch;

VHDL/SHIFTREGISTER_VHDL/sim1.vcd
$date
  Sat Jan 15 21:17:02 2022
$end
$version
  GHDL v0
$end
$timescale
  1 fs
$end
$scope module standard $end
$upscope $end
$scope module std_logic_1164 $end
$upscope $end
$scope module shiftregister_tb $end
$var reg 1 ! clk $end
$var reg 1 " s $end
$var reg 8 # p[7:0] $end
$scope module sr $end
$var reg 1 $ clk $end
$var reg 1 % s $end
$var reg 8 & p[7:0] $end
$var reg 8 ' p_in[7:0] $end
$upscope $end
$upscope $end
$enddefinitions $end
#0
0!
0"
bUUUUUUU0 #
0$
0%
bUUUUUUU0 &
bUUUUUUU0 '
#5
1"
1%
#10
1!
bUUUUUU01 #
1$
bUUUUUU01 &
bUUUUUU01 '
#15
0"
0%
#20
0!
bUUUUU010 #
0$
bUUUUU010 &
bUUUUU010 '
#30
1!
bUUUU0100 #
1$
bUUUU0100 &
bUUUU0100 '
#40
0!
bUUU01000 #
0$
bUUU01000 &
bUUU01000 '
#45
1"
1%
#50
1!
bUU010001 #
1$
bUU010001 &
bUU010001 '
#60
0!
bU0100011 #
0$
bU0100011 &
bU0100011 '
#70
1!
b01000111 #
1$
b01000111 &
b01000111 '
#80
0!
b10001111 #
0$
b10001111 &
b10001111 '
#90
1!
b00011111 #
1$
b00011111 &
b00011111 '
#95
0"
0%
#100
0!
1"
b00111111 #
0$
1%
b00111111 &
b00111111 '
#105
0"
0%
#110
1!
b01111110 #
1$
b01111110 &
b01111110 '
#115
1"
1%
#120
0!
b11111101 #
0$
b11111101 &
b11111101 '
#125
0"
0%
#130
1!
b11111010 #
1$
b11111010 &
b11111010 '
#135
1"
1%
#140
0!
b11110101 #
0$
b11110101 &
b11110101 '
#150
1!
b11101011 #
1$
b11101011 &
b11101011 '
#160
0!
b11010111 #
0$
b11010111 &
b11010111 '
#170
1!
b10101111 #
1$
b10101111 &
b10101111 '
#175
0"
0%
#180
0!
b01011110 #
0$
b01011110 &
b01011110 '
